pyobidl/downloader.py
pyobidl/googledrive.py
pyobidl/mediafire.py
pyobidl/utils.py
pyobidl/version.py
pyobidl/youtube.py
pyobidl/megacli/crypto.py
pyobidl/megacli/errors.py
pyobidl/megacli/mega.py
pyobidl/megacli/megafolder.py
pyobidl-1.1.0.dist-info/LICENSE
pyobidl-1.1.0.dist-info/METADATA
pyobidl-1.1.0.dist-info/WHEEL
pyobidl-1.1.0.dist-info/top_level.txt
pyobidl-1.1.0.dist-info/zip-safe
pyobidl-1.1.0.dist-info/RECORD
