Metadata-Version: 2.1
Name: pyobidl
Version: 1.1.0
Summary: Python 3 library for downloading (googledrive,mega,mediafire,directurl)
Home-page: https://github.com/ObisoftDev/pyobidl
Author: ObisoftDev
Author-email: obysoftt@gmail.com
License: The Unlicense (Unlicense)
Keywords: youtube,download,video,stream
Classifier: Development Status :: 5 - Production/Stable
Classifier: Environment :: Console
Classifier: Intended Audience :: Developers
Classifier: License :: OSI Approved :: The Unlicense (Unlicense)
Classifier: Natural Language :: English
Classifier: Operating System :: OS Independent
Classifier: Programming Language :: Python :: 3.6
Classifier: Programming Language :: Python :: 3.7
Classifier: Programming Language :: Python :: 3.8
Classifier: Programming Language :: Python :: 3.9
Classifier: Programming Language :: Python
Classifier: Topic :: Internet
Classifier: Topic :: Software Development :: Libraries :: Python Modules
Classifier: Topic :: Utilities
Requires-Python: >=3.6
License-File: LICENSE
Requires-Dist: requests
Requires-Dist: requests[socks]
Requires-Dist: requests-toolbelt
Requires-Dist: user-agent
Requires-Dist: mega
Requires-Dist: mega.py
